[{
	"id": "Basic",
	"name": "Basic",
	"zip": ["https://github.com/privat-allin/allin-data/blob/master/op_data/basic_userdata/basic_userdata-1.0.0.zip?raw=true"],
	"addons": ["repository.kodil","plugin.video.exodus","repository.all-in","repository.xbmc-israel","plugin.video.elysium"],
	"img": "http://i.imgur.com/aaaa.jpg",
	"fanart": "http://i.imgur.com/aaaa.jpg",
	"description": "Complete installation of the Kodi."
	"basic": "Complete installation of the Kodi."	
},
{
	"id": "AAAA",
	"name": "A Wizard",
	"zip": ["https://github.com/privat-allin/allin-data/blob/master/op_data/xonfluence.krypton.userdata/pack-1.0.zip?raw=true"],
	"addons": ["repository.kodil","plugin.video.exodus"],
	"img": "http://i.imgur.com/aaaa.jpg",
	"fanart": "http://i.imgur.com/aaaa.jpg",
	"description": "Complete installation of the Kodi."
},
{
	"id": "BBBB",
	"name": " BWizard",
	"zip": ["https://test.com/Kodi.Pack.[VER].zip"],
	"addons": ["plugin.audio.mixcloud","plugin.image.500px"],
	"img": "http://i.imgur.com/aaaa.jpg",
	"fanart": "http://i.imgur.com/aaaa.jpg",
	"description": "Complete installation of the Kodi."
}]